{
  "books": [
    {
      "id": "1",
      "title": "Pride and Prejudice",
      "author": "Jane Austen",
      "totalPages": 3,
      "currentPage": 3,
      "completed": true,
      "dateAdded": "2024-12-02 19:08:40"
    },
    {
      "id": "5",
      "title": "Little Women",
      "author": "Louisa May Alcott",
      "totalPages": 3,
      "currentPage": 3,
      "completed": true,
      "dateAdded": "2024-12-02 19:14:02"
    },
    {
      "id": "4",
      "title": "The Picture of Dorian Gray",
      "author": "Oscar Wilde",
      "totalPages": 7,
      "currentPage": 7,
      "completed": true,
      "dateAdded": "2024-12-02 20:54:02"
    },
    {
      "id": "8",
      "title": "Emily of New Moon",
      "author": "L.M. Montgomery",
      "totalPages": 2,
      "currentPage": 0,
      "completed": false,
      "dateAdded": "2024-12-03 12:07:20"
    },
    {
      "id": "9",
      "title": "The Hunchback of Notre-Dame",
      "author": "Victor Hugo",
      "totalPages": 5,
      "currentPage": 0,
      "completed": false,
      "dateAdded": "2024-12-03 12:07:25"
    }
  ]
}
